Workbook

Sheet Portada
B2: EKIO BIOTECH, S.L.U.
B3: Anexo financiero del Plan de Empresa
B4: Cuenta de crédito · Circulante de campaña Q4 2026 · CaixaBank
B6: CIF: B93860096
B7: Domicilio: Barrio de Arriba 39, 49327 Cubo de Benavente (Zamora)
B8: Socio único y administrador: Francisco Javier Andrés Andrés (NIF 09338115T)
B9: Fecha: 30 de agosto de 2026
B11: OBJETO
B12: Justificar la necesidad y la capacidad de devolución de una línea de circulante para financiar la compra anticipada de existencias (Spiro, Ekio Light y accesorios de medición) con la que atender la campaña de Q4 2026 (Black Friday + Navidad + Reyes). El importe que figura como solicitado es 250.000 €; el límite y la estructura los dimensiona la entidad.
B14: AVISOS
B15: · El histórico de 2023 está incompleto: solo consta la facturación (390.000 €); el margen bruto y el resultado de ese ejercicio quedan como [PENDIENTE].
B16: · Todas las cifras de P&L provienen del P&L de gestión de Holded (negocio del autónomo, continuado por la SLU) y deben contrastarse con el Holded actual antes de presentar.
... B25: 6. Escenarios (A base · B conservador · C disposición máxima)

Sheet Historico
B2: HISTÓRICO DE RESULTADOS (P&L de gestión Holded)
B3: Fuente: P&L Holded del negocio (autónomo continuado por la SLU). Contrastar con Holded actual.
B5: Ejercicio | C5: Facturación (€) | D5: Margen bruto | E5: Resultado (€)
B6: 2023 (jun–dic) | C6: 390000 | D6: n.d. [PENDIENTE] | E6: n.d. [PENDIENTE]
B7: 2024 | C7: 534504 | D7: 0.384 | E7: 52493
B8: 2025 | C8: 537845 | D8: 0.245 | E8: 19301
B9: 2026 (H1, ene–jun) | C9: 207815 | D9: 0.559 | E9: 78738
B10: ACUMULADA 2023 – jun 2026 | C10: =SUM(C6:C9)
B12: Nota: la cifra acumulada (≈ 1,67 M€) NO es facturación anual; es la suma de 2023 (jun–dic) + 2024 + 2025 + H1 2026. 2024, 2025 y H1 2026 cerraron en beneficios.

Sheet Supuestos
A1: SUPUESTOS — Parámetros editables
A2: Azul = input editable · Amarillo = [PENDIENTE] confirmar · Las hojas 2–6 referencian esta hoja.
A3: Parámetro | B3: Valor | C3: Unidad | D3: Notas / fuente
A4: 1 · Operación
A5: Importe solicitado de la línea | B5: 250000 | C5: € | D5: Cifra que la empresa desea solicitar (la dimensiona el banco)
A6: Objetivo de ventas campaña Q4 2026 | B6: 350000 | C6: € | D6: [PENDIENTE] confirmar objetivo de campaña real
A7: Campaña equivalente año anterior | B7: 275000 | C7: € | D7: BF+Navidad+Reyes año anterior (dato Javier)
A8: Crecimiento objetivo vs año anterior | B8: =B6/B7-1 | C8: % | D8: Fórmula
A9: 2 · Mix por categoría
A10: Categoría | B10: % de ventas | C10: Coste mercancía (COGS %)
A11: Spiro (distribución) | B11: 0.65 | C11: 0.6 | D11: [PENDIENTE] coste real por categoría
A12: Ekio Light (marca propia) | B12: 0.25 | C12: 0.45 | D12: [PENDIENTE] coste real por categoría
A13: Accesorios de medición | B13: 0.1 | C13: 0.55 | D13: [PENDIENTE] coste real por categoría
A14: Control (debe sumar 100%) | B14: =SUM(B11:B13)
A15: 3 · Distribución mensual de ventas
A16: oct-2026 | B16: 0.15
A17: nov-2026 | B17: 0.35
A18: dic-2026 | B18: 0.3
A19: ene-2027 | B19: 0.15
A20: feb-2027 | B20: 0.05
A21: Control (100%) | B21: =SUM(B16:B20)
A22: 4 · Compra de stock escalonada (pago en el mes de compra)
A23: oct-2026 | B23: 0.6
A24: nov-2026 | B24: 0.3
A25: dic-2026 | B25: 0.1
A26: Control (100%) | B26: =SUM(B23:B25)
A27: 5 · Otros parámetros
A28: Gastos de campaña (marketing+logística) | B28: 0.12 | C28: % ventas | D28: Sobre las ventas del mes
A29: Cuota mensual préstamo 70.000 € vivo | B29: 1350 | C29: €/mes | D29: [PENDIENTE] provisional; confirmar cuadro de amortización
A30: Meses de campaña (servicio de préstamo) | B30: 5 | C30: meses | D30: oct-2026 → feb-2027
A31: Cobro D2C | B31: Mes de la venta | D31: Venta directa: se cobra en el mes
A32: Plazo de pago a proveedor | B32: [PENDIENTE] | D32: [PENDIENTE] confirmar días de pago
A33: Reducción de ventas escenario B | B33: -0.25 | C33: % | D33: Escenario conservador: compras y gastos escalan con ventas

Sheet Necesidad de circulante
A1: NECESIDAD DE CIRCULANTE
A3: Importe solicitado de la línea | B3: =Supuestos!B5
A5: Categoría | B5: Ventas campaña (€) | C5: COGS % | D5: Coste de stock (€)
A6: Spiro (distribución) | B6: =Supuestos!$B$6*Supuestos!B11 | C6: =Supuestos!C11 | D6: =B6*C6
A7: Ekio Light (marca propia) | B7: =Supuestos!$B$6*Supuestos!B12 | C7: =Supuestos!C12 | D7: =B7*C7
A8: Accesorios de medición | B8: =Supuestos!$B$6*Supuestos!B13 | C8: =Supuestos!C13 | D8: =B8*C8
A9: TOTAL | B9: =SUM(B6:B8) | D9: =SUM(D6:D8)
A11: Coste total del stock de campaña | B11: =D9
A12: Headroom (línea − coste de stock) | B12: =B3-B11
A14: El headroom (≈ 54.875 €) da margen para reposiciones durante la propia campaña (roturas de stock en los picos de Black Friday y Reyes) y para el stock de arranque de Q1 2027, sin volver a disponer capital de la línea fuera del ciclo.

Sheet Flujo de caja campaña
A1: FLUJO DE CAJA DE CAMPAÑA — Escenario A (base, compra escalonada)
A3: Concepto (€) | B3: oct-2026 | C3: nov-2026 | D3: dic-2026 | E3: ene-2027 | F3: feb-2027 | G3: Total
A4: Cobros D2C (ventas del mes) | B4: =Supuestos!$B$6*Supuestos!B16 | C4: =Supuestos!$B$6*Supuestos!B17 | D4: =Supuestos!$B$6*Supuestos!B18 | E4: =Supuestos!$B$6*Supuestos!B19 | F4: =Supuestos!$B$6*Supuestos!B20 | G4: =SUM(B4:F4)
A5: Compra de stock (pago) | B5: ='Necesidad de circulante'!$D$9*Supuestos!B23 | C5: ='Necesidad de circulante'!$D$9*Supuestos!B24 | D5: ='Necesidad de circulante'!$D$9*Supuestos!B25 | E5: 0 | F5: 0 | G5: =SUM(B5:F5)
A6: Gastos de campaña | B6: =B4*Supuestos!$B$28 | C6: =C4*Supuestos!$B$28 | D6: =D4*Supuestos!$B$28 | E6: =E4*Supuestos!$B$28 | F6: =F4*Supuestos!$B$28 | G6: =SUM(B6:F6)
A7: Cuota préstamo 70k | B7: =Supuestos!$B$29 | C7: =Supuestos!$B$29 | D7: =Supuestos!$B$29 | E7: =Supuestos!$B$29 | F7: =Supuestos!$B$29 | G7: =SUM(B7:F7)
A8: Flujo libre del mes | B8: =B4-B5-B6-B7 | C8: =C4-C5-C6-C7 | D8: =D4-D5-D6-D7 | E8: =E4-E5-E6-E7 | F8: =F4-F5-F6-F7 | G8: =SUM(B8:F8)
A9: Flujo acumulado (pre-financiación) | B9: =B8 | C9: =B9+C8 | D9: =C9+D8 | E9: =D9+E8 | F9: =E9+F8
A10: Disposición de la línea (+) | B10: =MAX(0,B12) | C10: =MAX(0,C12-B12) | D10: =MAX(0,D12-C12) | E10: =MAX(0,E12-D12) | F10: =MAX(0,F12-E12) | G10: =SUM(B10:F10)
A11: Devolución de la línea (−) | B11: =MAX(0,-B12) | C11: =MAX(0,B12-C12) | D11: =MAX(0,C12-D12) | E11: =MAX(0,D12-E12) | F11: =MAX(0,E12-F12) | G11: =SUM(B11:F11)
A12: Saldo vivo de la línea (fin de mes) | B12: =MAX(0,-B9) | C12: =MAX(0,-C9) | D12: =MAX(0,-D9) | E12: =MAX(0,-E9) | F12: =MAX(0,-F9)
A13: Caja acumulada | B13: =MAX(0,B9) | C13: =MAX(0,C9) | D13: =MAX(0,D9) | E13: =MAX(0,E9) | F13: =MAX(0,F9)
A15: Pico de disposición de la línea | B15: =MAX(B12:F12)
A16: Flujo de caja operativo de campaña | B16: =G4-G5-G6
A17: Servicio del préstamo (5 meses) | B17: =Supuestos!B29*Supuestos!B30
A19: Lectura: el pico de disposición se produce en octubre y la línea queda totalmente devuelta a finales de diciembre (los cobros de nov+dic financian la devolución). La caja acumulada es positiva desde diciembre.

Sheet Escenarios
A1: ESCENARIOS DE DISPOSICIÓN Y COBERTURA
A3: Concepto | B3: A · Base (escalonada) | C3: B · Conservador (−25%) | D3: C · Disposición máxima
A4: Ventas de campaña (€) | B4: =Supuestos!$B$6 | C4: =Supuestos!$B$6*(1+Supuestos!$B$33) | D4: =Supuestos!$B$6
A5: Coste de stock (€) | B5: ='Necesidad de circulante'!$D$9 | C5: ='Necesidad de circulante'!$D$9*(1+Supuestos!$B$33) | D5: ='Necesidad de circulante'!$D$9
A6: Gastos de campaña (€) | B6: =B4*Supuestos!$B$28 | C6: =C4*Supuestos!$B$28 | D6: =D4*Supuestos!$B$28
A7: Flujo de caja operativo (€) | B7: =B4-B5-B6 | C7: =C4-C5-C6 | D7: =D4-D5-D6
A8: Pico de disposición de la línea (€) | B8: ='Flujo de caja campaña'!B15 | C8: =-(Supuestos!$B$6*(1+Supuestos!$B$33)*Supuestos!$B$16-'Necesidad de circulante'!$D$9*(1+Supuestos!$B$33)*Supuestos!$B$23-Supuestos!$B$6*(1+Supuestos!$B$33)*Supuestos!$B$16*Supuestos!$B$28-Supuestos!$B$29) | D8: =-(Supuestos!$B$6*Supuestos!$B$16-'Necesidad de circulante'!$D$9-Supuestos!$B$6*Supuestos!$B$16*Supuestos!$B$28-Supuestos!$B$29)
A9: Servicio del préstamo (5 meses) (€) | B9: =Supuestos!$B$29*Supuestos!$B$30 | C9: =Supuestos!$B$29*Supuestos!$B$30 | D9: =Supuestos!$B$29*Supuestos!$B$30
A10: Ratio de cobertura (flujo op. / (pico+servicio)) | B10: =B7/(B8+B9) | C10: =C7/(C8+C9) | D10: =D7/(D8+D9)
A11: Devuelta dentro de la campaña | B11: Sí (fin dic) | C11: Sí (fin dic) | D11: Sí (fin dic)
A13: Escenario C (extremo): se compra TODO el stock por adelantado en octubre. El pico es alto pero se autoliquida dentro de la campaña, porque nov+dic cobran 227.500 €. La cobertura sobre el pico es <1x, pero es un caso de estrés, no el plan base.
A14: Cobros nov+dic (control escenario C) | B14: =Supuestos!$B$6*Supuestos!$B$17+Supuestos!$B$6*Supuestos!$B$18
