Workbook

Sheet 00_Instrucciones
A1: CUESTIONARIO DE TITULARIDAD DE ACTIVOS — FASE 0 · EKIO BIOTECH S.L.
A2: Cliente: Francisco Javier Andrés Andrés · Fecha emisión: 2026-06-12 · Devolver cumplimentado en ≤ 7 días
A4: CÓMO RELLENAR
A5: 1. Recorre los 13 bloques (pestañas 01 a 13). Una fila por activo.
A6: 2. Rellena: TITULAR ACTUAL · DOCUMENTO · DESTINO. Cualquier celda en blanco se cuenta como pendiente en la pestaña 14_Tracker.
A7: 3. Si no sabes la respuesta, escribe REVISAR. Es respuesta válida y genera tarea.
A8: 4. Si no hay papel que acredite, escribe SIN DOCUMENTO.
A10: DESTINO — CÓDIGOS
A11: A = APORTAR a Ekio BioTech S.L. (vía aportación no dineraria).
A12: B = QUEDA en EKIO Bienestar S.L. (o futuro Ekio Holdings).
A13: C = QUEDA FUERA — patrimonio personal o tercero.
A14: D = DUDA — discutir con el agente o asesor antes de decidir.
... A27: Este cuestionario es apoyo técnico. Toda decisión final exige validación de asesor fiscal habilitado y notario.

Sheet 01_Stock
A1: BLOQUE 1 · STOCK Y PRODUCTO TERMINADO
A2: Ítem | B2: Titular actual | C2: Documento que lo acredita | D2: Destino (A/B/C/D) | E2: Valor estimado (€) | F2: Notas
A3: Stock panel Ekio Light Deep 5 (unidades + valor coste)
A4: Stock panel Ekio Light Bio Regén 7
A5: Stock panel Ekio Light Bio Spectrum 10
A6: Stock nuevo panel 13 LED (prototipos + producción si la hubiera)
A7: Stock línea Spiro en liquidación (unidades + valor neto realizable)
A8: Stock accesorios (cables, mandos, soportes, embalaje)
A9: Stock devoluciones / unidades defectuosas
A10: Stock en consigna / depósito con terceros (Amazon FBA, distribuidores)
A11: Materias primas y componentes electrónicos en almacén
A12: Stock obsoleto previsto para baja (provisión por deterioro)

Sheet 02_Equipamiento
A1: BLOQUE 2 · EQUIPAMIENTO E INMOVILIZADO
A2: Ítem | B2: Titular actual | C2: Documento que lo acredita | D2: Destino (A/B/C/D) | E2: Valor estimado (€) | F2: Notas
A3: Bancada de fabricación / herramientas de ensamblaje
A4: Equipo de medición (espectrómetro, lux/PAR meter, osciloscopio, EMF meter)
A5: Mobiliario, ordenadores, equipos oficina/taller
A6: Vehículo de empresa (si lo hay) — afectación 100% o mixta
A7: Local / nave / almacén — propiedad o alquiler
A8: Contrato de alquiler vigente (titular: Javier persona física / autónomo / Ekio Bienestar)
A9: Mejoras realizadas en local arrendado (reformas, instalaciones)
A10: Moldes / utillaje / fixtures de fabricación del panel

Sheet 03_Patentes
A1: BLOQUE 3 · PROPIEDAD INDUSTRIAL — PATENTES Y MODELOS ⚠️ CRÍTICO
A2: Ítem | B2: Titular actual | C2: Documento que lo acredita | D2: Destino (A/B/C/D) | E2: Valor estimado (€) | F2: Notas
A3: Modelo de utilidad U202532624 — solicitante registrado OEPM
A4: PCT — solicitud internacional 157 países (estado: en preparación/presentada)
A5: Designaciones nacionales previstas (US, EU, JP, CN, BR, IN, MX, KR, CA, AU…)
A6: Segunda patente SRBA (reemplaza SFPA) — estado redacción + solicitante previsto
A7: Patentes / modelos abandonados o caducados que conviene recuperar
A8: Eventual cesión interna previa (¿Javier cedió la MU a Ekio Bienestar SL?) — CRÍTICO

Sheet 04_Software
A1: BLOQUE 4 · SOFTWARE Y APLICACIONES PROPIAS
A2: Ítem | B2: Titular actual | C2: Documento que lo acredita | D2: Destino (A/B/C/D) | E2: Valor estimado (€) | F2: Notas
A3: SFPA (algoritmo fotobiomodulación) — código fuente + repositorio Git
A4: Algoritmo SRBA (sucesor de SFPA) — estado
A5: App Ekio Coach — código + cuentas App Store/Google Play + certificados
A6: Backend / API / base de datos asociada a la app
A7: Cuentas de hosting (AWS/GCP/Azure), dominios técnicos
A8: Software desarrollado por terceros con cesión exclusiva (¿hay contrato?)
A9: Software con licencia copyleft (GPL) embebido — auditoría legal pendiente

Sheet 05_Marcas
A1: BLOQUE 5 · MARCAS Y SIGNOS DISTINTIVOS
A2: Ítem | B2: Titular actual | C2: Documento que lo acredita | D2: Destino (A/B/C/D) | E2: Valor estimado (€) | F2: Notas
A3: Marca EKIO denominativa — OEPM
A4: Marca EKIO mixta/figurativa (logo) — OEPM
A5: Marca EKIO LIGHT — registrada / en trámite / no registrada
A6: Marca EKIO BIOTECH — disponibilidad y reserva (búsqueda OEPM/EUIPO)
A7: Marca EKIO COACH
A8: Marca DEEP / BIO REGÉN / BIO SPECTRUM
A9: Marca Electrosmog España (denominativa o figurativa)
A10: Marca SPIRO (si EKIO la usaba como marca propia)
A11: Marcas UE (EUIPO) — alguna registrada
A12: Marcas internacionales (Sistema Madrid OMPI)
A13: Diseños industriales registrados (packaging, panel design)

Sheet 06_Dominios
A1: BLOQUE 6 · DOMINIOS WEB
A2: Dominio | B2: Titular actual (registrant) | C2: Registrador / Documento | D2: Destino (A/B/C/D) | E2: Notas
A3: electrosmogespana.com
A4: ekio.es
A5: ekio.com (si está)
A6: ekiolight.com / .es
A7: ekiobiotech.com / .es (disponibilidad y reserva inmediata)
A8: ekiocoach.com / .es
A9: ekiobienestar.es / .com
A10: Otros dominios históricos (webs antiguas, microsites de campañas)
A11: Dominios defensivos (typo-squatting, regiones)
A12: Certificados SSL y emails @dominio (Google Workspace / Microsoft 365)

Sheet 07_Webs_Shopify
A1: BLOQUE 7 · WEBS Y TIENDA ONLINE
A2: Ítem | B2: Titular actual | C2: Documento que lo acredita | D2: Destino (A/B/C/D) | E2: Notas
A3: Tienda Shopify electrosmogespana.com — cuenta admin, plan, facturación
A4: Tema Dawn personalizado — versiones, customizaciones, código propio
A5: Apps Shopify de pago contratadas (Klaviyo connector, reviews, etc.)
A6: Webs históricas (versiones antiguas, blog, landing pages legacy)
A7: Landing pages externas (Carrd, Webflow, Wordpress)
A8: Hosting de webs no-Shopify (Wordpress)
A9: Backups históricos de la tienda y blog

Sheet 08_RRSS_Marketing
A1: BLOQUE 8 · REDES SOCIALES Y CUENTAS DE MARKETING
A2: Cuenta | B2: Titular actual (email admin / facturación) | C2: Documento | D2: Destino (A/B/C/D) | E2: Notas
A3: Instagram @ekio… (handle exacto) — Meta Business titular
A4: TikTok
A5: YouTube (canal, AdSense si activado)
A6: Facebook Page + Business Manager
A7: LinkedIn Página de Empresa
A8: Pinterest
A9: Twitter/X
A10: Pixel Meta — propiedad y eventos
A11: Cuenta Google Ads — facturación a quién
A12: Google Merchant Center
A13: Google Analytics 4 — propiedad, admins
A14: Google Search Console (electrosmogespana.com)
... A19: Herramientas SEO contratadas (Ahrefs, SEMrush)

Sheet 09_BBDD_RGPD
A1: BLOQUE 9 · BASES DE DATOS Y RGPD ⚠️ BANDERA ROJA #4
A2: Ítem | B2: Titular actual | C2: Base lícita RGPD / Documento | D2: Destino (A/B/C/D) | E2: Notas
A3: Lista Klaviyo 12.400 contactos — base lícita del tratamiento (consentimiento, contrato, interés legítimo)
A4: Cartera 7.600 clientes (datos transaccionales Shopify)
A5: Lista WhatsApp / SMS opt-in
A6: Base de seguidores ManyChat (IG/WhatsApp)
A7: Encuestas históricas, NPS, feedback de clientes
A8: Audiencias custom Meta (Lookalikes, retargeting)
A9: Acuerdo Encargado del Tratamiento con cada proveedor (Klaviyo, Shopify, ManyChat) — a nombre de quién

Sheet 10_Contratos
A1: BLOQUE 10 · CONTRATOS COMERCIALES Y PROVEEDORES
A2: Contrato | B2: Parte contratante actual | C2: Documento | D2: Destino (A/B/C/D) | E2: Notas
A3: Fabricante / ensamblador de los paneles — contrato OEM, exclusividad
A4: Proveedores de componentes electrónicos (LEDs, drivers, PCB)
A5: Proveedor de packaging
A6: Operador logístico / fulfillment
A7: Transportistas (UPS, SEUR, GLS, courier internacional)
A8: Pasarela de pago Stripe / Shopify Payments — titular cuenta
A9: PayPal Business
A10: Bizum empresa
A11: Cuentas bancarias asociadas (titular: persona física / autónomo / Ekio Bienestar)
A12: Contratos de distribución (si EKIO distribuye productos de terceros)
A13: Contratos de marca blanca / OEM salientes
A14: Acuerdos con afiliados / embajadores / influencers
... A17: Suscripciones de soft empresarial (Holded, Quipu, A3, Notion, Slack…)

Sheet 11_Equipo
A1: BLOQUE 11 · EQUIPO HUMANO (~8 PERSONAS)
A2: Persona / Rol | B2: Régimen (asalariado RGSS/autónomo factura/TRADE/phantom/F&F) | C2: Quién paga hoy | D2: Documento (contrato laboral/mercantil/sin contrato) | E2: Antigüedad | F2: Destino (A/B/C/D)
A3: Erick — especialista Klaviyo
A4: Operaciones / fulfillment
A5: Atención cliente / postventa
A6: Diseño / creatividad
A7: Contenido / redes sociales
A8: Comercial / B2B
A9: I+D / técnico paneles
A10: Administración / contable
A11: Marta Andrés Andrés (phantom equity cerrado) — régimen laboral subyacente
A12: José Luis Herreros (phantom equity cerrado) — régimen laboral subyacente
A13: María del Rosario Curvelo (phantom equity cerrado) — régimen laboral subyacente

Sheet 12_Pasivos
A1: BLOQUE 12 · PASIVOS, DEUDAS Y CONTINGENCIAS
A2: Ítem | B2: Titular / Deudor | C2: Documento | D2: Importe pendiente (€) | E2: Destino (A/B/C/D)
A3: Préstamo ICO (si existe) — capital pendiente, cuota, garantías
A4: Otros préstamos bancarios o pólizas de crédito
A5: Línea de crédito Shopify Capital / Klarna / PayPal Working Capital
A6: Confirming / factoring activo
A7: Aplazamientos AEAT (IS, IVA, IRPF)
A8: Aplazamientos Seguridad Social
A9: Deudas con proveedores > 60 días
A10: Devoluciones pendientes / chargebacks abiertos
A11: Reclamaciones de consumidores / OCU / Junta arbitral
A12: Litigios abiertos (cualquier parte)
A13: Inspecciones AEAT o SS en curso o recientes
A14: Subvenciones recibidas con compromisos (CDTI, ICEX, ENISA, ICE CyL, AEI)
... A16: Seguros (RC producto, ciber, multirriesgo local) — titular póliza

Sheet 13_Intangibles_blandos
A1: BLOQUE 13 · INTANGIBLES BLANDOS (NO CAPITALIZABLES AISLADOS)
A2: Ítem | B2: Estado | C2: Documento si existe | D2: Notas para due diligence
A3: Know-how de formulación / protocolos de uso de paneles
A4: Documentación clínica recopilada (estudios, mediciones)
A5: Marca personal de Javier (presencia pública, charlas, Foro)
A6: Comunidad / fan base orgánica
A7: Relaciones con prescriptores / KOLs del sector
A8: Material formativo FBM (videos, cursos, PDFs)
A9: Reviews / testimonios / casos de éxito documentados

Sheet 14_Tracker
A1: TRACKER DE PROGRESO — FASE 0
A2: Bloque | B2: Total ítems | C2: Rellenados (titular ≠ vacío) | D2: REVISAR | E2: % Completado
A3: BLOQUE 1 · STOCK Y PRODUCTO TERMINADO | B3: 10 | C3: =COUNTA('01_Stock'!B3:B12) | D3: =COUNTIF('01_Stock'!B3:F12,"REVISAR") | E3: =IFERROR(C3/B3,0)
A4: BLOQUE 2 · EQUIPAMIENTO E INMOVILIZADO | B4: 8 | C4: =COUNTA('02_Equipamiento'!B3:B10) | D4: =COUNTIF('02_Equipamiento'!B3:F10,"REVISAR") | E4: =IFERROR(C4/B4,0)
A5: BLOQUE 3 · PROPIEDAD INDUSTRIAL — PATENTES Y MODELOS ⚠️ CRÍ | B5: 6 | C5: =COUNTA('03_Patentes'!B3:B8) | D5: =COUNTIF('03_Patentes'!B3:F8,"REVISAR") | E5: =IFERROR(C5/B5,0)
A6: BLOQUE 4 · SOFTWARE Y APLICACIONES PROPIAS | B6: 7 | C6: =COUNTA('04_Software'!B3:B9) | D6: =COUNTIF('04_Software'!B3:F9,"REVISAR") | E6: =IFERROR(C6/B6,0)
A7: BLOQUE 5 · MARCAS Y SIGNOS DISTINTIVOS | B7: 11 | C7: =COUNTA('05_Marcas'!B3:B13) | D7: =COUNTIF('05_Marcas'!B3:F13,"REVISAR") | E7: =IFERROR(C7/B7,0)
A8: BLOQUE 6 · DOMINIOS WEB | B8: 10 | C8: =COUNTA('06_Dominios'!B3:B12) | D8: =COUNTIF('06_Dominios'!B3:F12,"REVISAR") | E8: =IFERROR(C8/B8,0)
A9: BLOQUE 7 · WEBS Y TIENDA ONLINE | B9: 7 | C9: =COUNTA('07_Webs_Shopify'!B3:B9) | D9: =COUNTIF('07_Webs_Shopify'!B3:F9,"REVISAR") | E9: =IFERROR(C9/B9,0)
A10: BLOQUE 8 · REDES SOCIALES Y CUENTAS DE MARKETING | B10: 17 | C10: =COUNTA('08_RRSS_Marketing'!B3:B19) | D10: =COUNTIF('08_RRSS_Marketing'!B3:F19,"REVISAR") | E10: =IFERROR(C10/B10,0)
A11: BLOQUE 9 · BASES DE DATOS Y RGPD ⚠️ BANDERA ROJA #4 | B11: 7 | C11: =COUNTA('09_BBDD_RGPD'!B3:B9) | D11: =COUNTIF('09_BBDD_RGPD'!B3:F9,"REVISAR") | E11: =IFERROR(C11/B11,0)
A12: BLOQUE 10 · CONTRATOS COMERCIALES Y PROVEEDORES | B12: 15 | C12: =COUNTA('10_Contratos'!B3:B17) | D12: =COUNTIF('10_Contratos'!B3:F17,"REVISAR") | E12: =IFERROR(C12/B12,0)
A13: BLOQUE 11 · EQUIPO HUMANO (~8 PERSONAS) | B13: 11 | C13: =COUNTA('11_Equipo'!B3:B13) | D13: =COUNTIF('11_Equipo'!B3:F13,"REVISAR") | E13: =IFERROR(C13/B13,0)
A14: BLOQUE 12 · PASIVOS, DEUDAS Y CONTINGENCIAS | B14: 14 | C14: =COUNTA('12_Pasivos'!B3:B16) | D14: =COUNTIF('12_Pasivos'!B3:F16,"REVISAR") | E14: =IFERROR(C14/B14,0)
A15: BLOQUE 13 · INTANGIBLES BLANDOS (NO CAPITALIZABLES AISLADOS) | B15: 7 | C15: =COUNTA('13_Intangibles_blandos'!B3:B9) | D15: =COUNTIF('13_Intangibles_blandos'!B3:F9,"REVISAR") | E15: =IFERROR(C15/B15,0)
A16: TOTAL | B16: =SUM(B3:B15) | C16: =SUM(C3:C15) | D16: =SUM(D3:D15) | E16: =IFERROR(C16/B16,0)
A18: Nota: el contador 'Rellenados' cuenta filas con la columna 'Titular actual' (B) cumplimentada. 'REVISAR' se cuenta en todas las columnas B-F.
